cld4py/__init__.py
cld4py/cld4py.py
cld4py-1.1.2.dist-info/METADATA
cld4py-1.1.2.dist-info/WHEEL
cld4py-1.1.2.dist-info/top_level.txt
cld4py-1.1.2.dist-info/RECORD
