Metadata-Version: 2.1
Name: cld4py
Version: 1.1.2
Summary: Python 3 function to assign compact letter display letters and for plotting them with matplotlib/seaborn
Author-email: Timur Yergaliyev <timyerg@gmail.com>
Project-URL: Homepage, https://github.com/timyerg/cld4py
Project-URL: Bug Tracker, https://github.com/timyerg/cld4py/issues
Classifier: Programming Language :: Python :: 3
Classifier: License :: OSI Approved :: Apache Software License
Classifier: Operating System :: OS Independent
Requires-Python: >=3.7
